[
  {
    "Total": "91.1",
    "Male": "92.6",
    "Female": "89.7",
    "Urban": "93.4",
    "Sector Rural": "91.7",
    "Estate": "75.1",
    "District": "Total (18 districts)"
  },
  {
    "Total": "94.7",
    "Male": "95.3",
    "Female": "94.0",
    "Urban": "93.3",
    "Sector Rural": "96.4",
    "Estate": "82.0",
    "District": "Colombo"
  },
  {
    "Total": "95.4",
    "Male": "95.7",
    "Female": "95.1",
    "Urban": "93.7",
    "Sector Rural": "95.7",
    "Estate": "88.0",
    "District": "Gampaha"
  },
  {
    "Total": "93.2",
    "Male": "93.7",
    "Female": "92.6",
    "Urban": "93.6",
    "Sector Rural": "93.7",
    "Estate": "77.5",
    "District": "Kalutara"
  },
  {
    "Total": "90.5",
    "Male": "92.4",
    "Female": "88.7",
    "Urban": "94.7",
    "Sector Rural": "91.2",
    "Estate": "74.6",
    "District": "Kandy"
  },
  {
    "Total": "88.3",
    "Male": "90.2",
    "Female": "86.4",
    "Urban": "93.9",
    "Sector Rural": "88.5",
    "Estate": "75.7",
    "District": "Matale"
  },
  {
    "Total": "82.6",
    "Male": "87.6",
    "Female": "77.7",
    "Urban": "92.9",
    "Sector Rural": "88.9",
    "Estate": "76.6",
    "District": "Nuwara Eliya"
  },
  {
    "Total": "92.3",
    "Male": "93.2",
    "Female": "91.5",
    "Urban": "94.9",
    "Sector Rural": "92.5",
    "Estate": "64.3",
    "District": "Galle"
  },
  {
    "Total": "90.3",
    "Male": "91.9",
    "Female": "88.9",
    "Urban": "95.9",
    "Sector Rural": "90.8",
    "Estate": "53.3",
    "District": "Matara"
  },
  {
    "Total": "88.9",
    "Male": "90.9",
    "Female": "87.0",
    "Urban": "93.6",
    "Sector Rural": "88.9",
    "Estate": "57.2",
    "District": "Hambantota"
  },
  {
    "Total": "85.9",
    "Male": "88.9",
    "Female": "82.9",
    "Urban": "88.9",
    "Sector Rural": "85.2",
    "District": "Ampara -"
  },
  {
    "Total": "92.7",
    "Male": "93.9",
    "Female": "91.5",
    "Urban": "94.8",
    "Sector Rural": "92.7",
    "Estate": "81.0",
    "District": "Kurunegala"
  },
  {
    "Total": "90.7",
    "Male": "91.2",
    "Female": "90.3",
    "Urban": "88.3",
    "Sector Rural": "91.0",
    "Estate": "82.2",
    "District": "Puttalam"
  },
  {
    "Total": "90.5",
    "Male": "92.0",
    "Female": "88.8",
    "Urban": "96.0",
    "Sector Rural": "90.0",
    "Estate": "96.4",
    "District": "Anuradhapura"
  },
  {
    "Total": "90.0",
    "Male": "91.2",
    "Female": "88.7",
    "Sector Rural": "90.0",
    "Estate": "93.2",
    "District": "Polonnaruwa -"
  },
  {
    "Total": "85.2",
    "Male": "88.9",
    "Female": "81.7",
    "Urban": "93.8",
    "Sector Rural": "87.1",
    "Estate": "75.8",
    "District": "Badulla"
  },
  {
    "Total": "86.0",
    "Male": "88.1",
    "Female": "83.8",
    "Sector Rural": "86.2",
    "Estate": "77.2",
    "District": "Moneragala -"
  },
  {
    "Total": "88.4",
    "Male": "90.4",
    "Female": "86.2",
    "Urban": "94.3",
    "Sector Rural": "89.8",
    "Estate": "72.3",
    "District": "Ratnapura"
  },
  {
    "Total": "91.4",
    "Male": "93.0",
    "Female": "89.8",
    "Urban": "94.6",
    "Sector Rural": "92.5",
    "Estate": "75.0",
    "District": "Kegalle"
  }
]